Workbook

Sheet Summary
A1: Apple Inc. (AAPL) — Valuation Summary
A2: Prepared 2026-07-19 · all data via Yahoo Finance · $ in billions unless per-share
A4: Valuation by method | B4: Value/share | C4: vs current
A5: DCF (Gordon growth) | B5: =DCF!B15 -> 142.04752 | C5: =B5/$B$8-1 -> -0.57437671
A6: Peer-median forward P/E | B6: =Comps!B12 -> 157.19195 | C6: =B6/$B$8-1 -> -0.52899878
A7: Analyst mean target | B7: =Assumptions!B32 -> 318.25 | C7: =B7/$B$8-1 -> -0.046413376
A8: Current market price | B8: =Assumptions!B29 -> 333.74
A10: Model valuation range | B10: =MIN(B5:B7) -> 142.04752 | C10: =MAX(B5:B7) -> 318.25
A12: Reading the gap
A13: All three methods land below the current price: the market is paying a large premium to both an
A14: intrinsic-cash-flow view and to peer multiples (AAPL trades ~40x trailing vs peer median ~25x).
A15: That premium is the bet: it requires either a step-change in growth (AI supercycle, services
A16: acceleration like the +16.6% Mar-2026 quarter continuing) or sustained multiple expansion.
A18: Bull case
A19: Revenue re-acceleration holds high-single/low-double digits; margins keep inching up on services;
A20: buybacks shrink the share count ~3%/yr (not modeled — upside to per-share figures).
A21: Bear case
A22: Growth mean-reverts to FY23-25 trend (0-6%); multiple compresses toward peers; DCF (~B5) becomes the anchor.
A24: The 3 assumptions this valuation is most sensitive to
A25: 1. WACC — each 0.5pt move shifts DCF value roughly 10-15% (see DCF sensitivity grid).
... A29: This is an educational model, not investment advice.

Sheet Assumptions
A1: AAPL — Model Assumptions
A2: Blue = hardcoded input (edit these). Yellow = key value drivers. All $ in billions.
B3: FY2026E | C3: FY2027E | D3: FY2028E | E3: FY2029E | F3: FY2030E
A4: Revenue growth % | B4: 0.08 | C4: 0.07 | D4: 0.06 | E4: 0.05 | F4: 0.045 | H4: FY25 grew 6.4%; last two quarters ran +16.6% YoY — base case tapers from 8%
A5: Gross margin % | B5: 0.47 | C5: 0.471 | D5: 0.472 | E5: 0.473 | F5: 0.474 | H5: FY25 actual 46.9%; slight services-mix-driven expansion
A6: R&D % of revenue | B6: 0.083 | C6: 0.083 | D6: 0.083 | E6: 0.083 | F6: 0.083 | H6: FY25 actual 8.3%
A7: SG&A % of revenue | B7: 0.066 | C7: 0.066 | D7: 0.066 | E7: 0.066 | F7: 0.066 | H7: FY25 actual 6.6%
A8: Tax rate | B8: 0.16 | C8: 0.16 | D8: 0.16 | E8: 0.16 | F8: 0.16 | H8: FY25 effective rate 15.6% (FY24's 24% was a one-off EU state-aid charge)
A9: D&A % of revenue | B9: 0.028 | C9: 0.028 | D9: 0.028 | E9: 0.028 | F9: 0.028 | H9: FY25 actual 2.8%
A10: Capex % of revenue | B10: 0.03 | C10: 0.03 | D10: 0.03 | E10: 0.03 | F10: 0.03 | H10: FY25 actual 3.1%
A11: Receivables % of revenue | B11: 0.096 | C11: 0.096 | D11: 0.096 | E11: 0.096 | F11: 0.096 | H11: FY25 actual 9.6%
A12: Inventory % of revenue | B12: 0.014 | C12: 0.014 | D12: 0.014 | E12: 0.014 | F12: 0.014 | H12: FY25 actual 1.4%
A13: Payables % of revenue | B13: 0.168 | C13: 0.168 | D13: 0.168 | E13: 0.168 | F13: 0.168 | H13: FY25 actual 16.8%
A14: Share repurchases ($bn) | B14: 95 | C14: 95 | D14: 95 | E14: 95 | F14: 95 | H14: FY22-25 average ~$88bn/yr
A15: Dividends ($bn) | B15: 15.5 | C15: 15.8 | D15: 16.1 | E15: 16.4 | F15: 16.7 | H15: FY25 $15.4bn, grown ~2%/yr
A17: WACC (CAPM)
A18: Risk-free rate (US 10Y) | B18: 0.0454 | H18: Yahoo Finance ^TNX close, 2026-07-18
A19: Beta | B19: 1.1 | H19: Yahoo Finance 5Y monthly beta
A20: Equity risk premium | B20: 0.045 | H20: Standard 4.5% assumption (Damodaran-range)
A21: Cost of equity | B21: =B18+B19*B20 -> 0.0949 | H21: CAPM: rf + beta x ERP
A22: Pre-tax cost of debt | B22: 0.04 | H22: Approx. AAPL long-bond yield; user-adjustable
A23: Market cap ($bn) | B23: 4901.8 | H23: Yahoo Finance, 2026-07-18
A24: Total debt ($bn) | B24: 84.7 | H24: Most recent quarter, Yahoo Finance
A25: WACC | B25: =(B23*B21+B24*B22*(1-B8))/(B23+B24) -> 0.093858767 | H25: Market-value weighted
A26: Terminal growth rate | B26: 0.03 | H26: Long-run nominal GDP-ish growth
A28: Market data
A29: Current share price | B29: 333.74 | H29: Yahoo Finance close, 2026-07-18
A30: Diluted shares (bn) | B30: 14.687 | H30: Yahoo Finance shares outstanding; held flat in projections (conservative — ignores buyback shrink)
A31: Net debt ($bn) | B31: 16.2 | H31: Total debt less total cash, most recent quarter
A32: Analyst mean target | B32: 318.25 | H32: Yahoo Finance consensus
A34: Source: Yahoo Finance API pull 2026-07-19. Fiscal years end late September.

Sheet IncomeStatement
A1: AAPL — Income Statement ($bn)
B2: FY2022 | C2: FY2023 | D2: FY2024 | E2: FY2025 | F2: FY2026E | G2: FY2027E | H2: FY2028E | I2: FY2029E | J2: FY2030E
A3: Revenue | B3: 394.33 | C3: 383.29 | D3: 391.04 | E3: 416.16 | F3: =E3*(1+Assumptions!B4) -> 449.4528 | G3: =F3*(1+Assumptions!C4) -> 480.9145 | H3: =G3*(1+Assumptions!D4) -> 509.76937 | I3: =H3*(1+Assumptions!E4) -> 535.25783 | J3: =I3*(1+Assumptions!F4) -> 559.34444
A4: growth % | C4: =C3/B3-1 -> -0.027996855 | D4: =D3/C3-1 -> 0.020219677 | E4: =E3/D3-1 -> 0.064238953 | F4: =F3/E3-1 -> 0.08 | G4: =G3/F3-1 -> 0.07 | H4: =H3/G3-1 -> 0.06 | I4: =I3/H3-1 -> 0.05 | J4: =J3/I3-1 -> 0.045
A5: Cost of revenue | B5: 223.55 | C5: 214.14 | D5: 210.35 | E5: 220.96 | F5: =F3*(1-Assumptions!B5) -> 238.20998 | G5: =G3*(1-Assumptions!C5) -> 254.40377 | H5: =H3*(1-Assumptions!D5) -> 269.15823 | I5: =I3*(1-Assumptions!E5) -> 282.08088 | J5: =J3*(1-Assumptions!F5) -> 294.21517
A6: Gross profit | B6: =B3-B5 -> 170.78 | C6: =C3-C5 -> 169.15 | D6: =D3-D5 -> 180.69 | E6: =E3-E5 -> 195.2 | F6: =F3-F5 -> 211.24282 | G6: =G3-G5 -> 226.51073 | H6: =H3-H5 -> 240.61114 | I6: =I3-I5 -> 253.17696 | J6: =J3-J5 -> 265.12926
A7: gross margin % | B7: =B6/B3 -> 0.43308904 | C7: =C6/C3 -> 0.44131076 | D7: =D6/D3 -> 0.46207549 | E7: =E6/E3 -> 0.46905037 | F7: =F6/F3 -> 0.47 | G7: =G6/G3 -> 0.471 | H7: =H6/H3 -> 0.472 | I7: =I6/I3 -> 0.473 | J7: =J6/J3 -> 0.474
A8: Research & development | B8: 26.25 | C8: 29.91 | D8: 31.37 | E8: 34.55 | F8: =F3*Assumptions!B6 -> 37.304582 | G8: =G3*Assumptions!C6 -> 39.915903 | H8: =H3*Assumptions!D6 -> 42.310857 | I8: =I3*Assumptions!E6 -> 44.4264 | J8: =J3*Assumptions!F6 -> 46.425588
A9: Selling, general & admin | B9: 25.09 | C9: 24.93 | D9: 26.1 | E9: 27.6 | F9: =F3*Assumptions!B7 -> 29.663885 | G9: =G3*Assumptions!C7 -> 31.740357 | H9: =H3*Assumptions!D7 -> 33.644778 | I9: =I3*Assumptions!E7 -> 35.327017 | J9: =J3*Assumptions!F7 -> 36.916733
A10: Operating income (EBIT) | B10: =B6-B8-B9 -> 119.44 | C10: =C6-C8-C9 -> 114.31 | D10: =D6-D8-D9 -> 123.22 | E10: =E6-E8-E9 -> 133.05 | F10: =F6-F8-F9 -> 144.27435 | G10: =G6-G8-G9 -> 154.85447 | H10: =H6-H8-H9 -> 164.65551 | I10: =I6-I8-I9 -> 173.42354 | J10: =J6-J8-J9 -> 181.78694
A11: EBIT margin % | B11: =B10/B3 -> 0.30289352 | C11: =C10/C3 -> 0.29823371 | D11: =D10/D3 -> 0.31510843 | E11: =E10/E3 -> 0.31970877 | F11: =F10/F3 -> 0.321 | G11: =G10/G3 -> 0.322 | H11: =H10/H3 -> 0.323 | I11: =I10/I3 -> 0.324 | J11: =J10/J3 -> 0.325
A12: Other income/(expense) | B12: -0.34 | C12: -0.56 | D12: 0.26 | E12: -0.32 | F12: 0 | G12: 0 | H12: 0 | I12: 0 | J12: 0
A13: Pretax income | B13: =B10+B12 -> 119.1 | C13: =C10+C12 -> 113.75 | D13: =D10+D12 -> 123.48 | E13: =E10+E12 -> 132.73 | F13: =F10+F12 -> 144.27435 | G13: =G10+G12 -> 154.85447 | H13: =H10+H12 -> 164.65551 | I13: =I10+I12 -> 173.42354 | J13: =J10+J12 -> 181.78694
A14: Income tax | B14: 19.3 | C14: 16.74 | D14: 29.75 | E14: 20.72 | F14: =F13*Assumptions!B8 -> 23.083896 | G14: =G13*Assumptions!C8 -> 24.776715 | H14: =H13*Assumptions!D8 -> 26.344881 | I14: =I13*Assumptions!E8 -> 27.747766 | J14: =J13*Assumptions!F8 -> 29.085911
A15: effective tax rate | B15: =B14/B13 -> 0.1620487 | C15: =C14/C13 -> 0.14716484 | D15: =D14/D13 -> 0.24092971 | E15: =E14/E13 -> 0.15610638 | F15: =F14/F13 -> 0.16 | G15: =G14/G13 -> 0.16 | H15: =H14/H13 -> 0.16 | I15: =I14/I13 -> 0.16 | J15: =J14/J13 -> 0.16
A16: Net income | B16: =B13-B14 -> 99.8 | C16: =C13-C14 -> 97.01 | D16: =D13-D14 -> 93.73 | E16: =E13-E14 -> 112.01 | F16: =F13-F14 -> 121.19045 | G16: =G13-G14 -> 130.07775 | H16: =H13-H14 -> 138.31062 | I16: =I13-I14 -> 145.67577 | J16: =J13-J14 -> 152.70103
A17: Diluted shares (bn) | B17: 16.33 | C17: 15.81 | D17: 15.41 | E17: 15 | F17: =Assumptions!$B$30 -> 14.687 | G17: =Assumptions!$B$30 -> 14.687 | H17: =Assumptions!$B$30 -> 14.687 | I17: =Assumptions!$B$30 -> 14.687 | J17: =Assumptions!$B$30 -> 14.687
A18: Diluted EPS | B18: =B16/B17 -> 6.1114513 | C18: =C16/C17 -> 6.1359899 | D18: =D16/D17 -> 6.082414 | E18: =E16/E17 -> 7.4673333 | F18: =F16/F17 -> 8.2515458 | G18: =G16/G17 -> 8.8566591 | H18: =H16/H17 -> 9.4172142 | I18: =I16/I17 -> 9.9186881 | J18: =J16/J17 -> 10.39702
A20: Historical figures: Apple 10-K filings via Yahoo Finance. Projections driven by Assumptions tab.

Sheet BalanceSheet
A1: AAPL — Balance Sheet, simplified ($bn)
B2: FY2022 | C2: FY2023 | D2: FY2024 | E2: FY2025 | F2: FY2026E | G2: FY2027E | H2: FY2028E | I2: FY2029E | J2: FY2030E
A3: Cash & investments | B3: 48.3 | C3: 61.55 | D3: 65.17 | E3: 54.7 | F3: =E3+CashFlow!F12 -> 66.19981 | G3: =F3+CashFlow!G12 -> 86.340512 | H3: =G3+CashFlow!H12 -> 114.20518 | I3: =H3+CashFlow!I12 -> 148.88877 | J3: =I3+CashFlow!J12 -> 190.16813
A4: Accounts receivable | B4: 28.18 | C4: 29.51 | D4: 33.41 | E4: 39.78 | F4: =IncomeStatement!F3*Assumptions!B11 -> 43.147469 | G4: =IncomeStatement!G3*Assumptions!C11 -> 46.167792 | H4: =IncomeStatement!H3*Assumptions!D11 -> 48.937859 | I4: =IncomeStatement!I3*Assumptions!E11 -> 51.384752 | J4: =IncomeStatement!J3*Assumptions!F11 -> 53.697066
A5: Inventory | B5: 4.95 | C5: 6.33 | D5: 7.29 | E5: 5.72 | F5: =IncomeStatement!F3*Assumptions!B12 -> 6.2923392 | G5: =IncomeStatement!G3*Assumptions!C12 -> 6.7328029 | H5: =IncomeStatement!H3*Assumptions!D12 -> 7.1367711 | I5: =IncomeStatement!I3*Assumptions!E12 -> 7.4936097 | J5: =IncomeStatement!J3*Assumptions!F12 -> 7.8308221
A6: Other current assets | B6: 53.98 | C6: 46.18 | D6: 47.12 | E6: 47.76 | F6: =E6 -> 47.76 | G6: =F6 -> 47.76 | H6: =G6 -> 47.76 | I6: =H6 -> 47.76 | J6: =I6 -> 47.76
A7: Total current assets | B7: =SUM(B3:B6) -> 135.41 | C7: =SUM(C3:C6) -> 143.57 | D7: =SUM(D3:D6) -> 152.99 | E7: =SUM(E3:E6) -> 147.96 | F7: =SUM(F3:F6) -> 163.39962 | G7: =SUM(G3:G6) -> 187.00111 | H7: =SUM(H3:H6) -> 218.03981 | I7: =SUM(I3:I6) -> 255.52713 | J7: =SUM(J3:J6) -> 299.45602
A8: Net PP&E | B8: 42.12 | C8: 43.72 | D8: 45.68 | E8: 49.83 | F8: =E8-CashFlow!F8-CashFlow!F4 -> 50.728906 | G8: =F8-CashFlow!G8-CashFlow!G4 -> 51.690735 | H8: =G8-CashFlow!H8-CashFlow!H4 -> 52.710273 | I8: =H8-CashFlow!I8-CashFlow!I4 -> 53.780789 | J8: =I8-CashFlow!J8-CashFlow!J4 -> 54.899478
A9: Other non-current assets | B9: 175.22 | C9: 165.29 | D9: 166.31 | E9: 161.45 | F9: =E9 -> 161.45 | G9: =F9 -> 161.45 | H9: =G9 -> 161.45 | I9: =H9 -> 161.45 | J9: =I9 -> 161.45
A10: Total assets | B10: =B7+B8+B9 -> 352.75 | C10: =C7+C8+C9 -> 352.58 | D10: =D7+D8+D9 -> 364.98 | E10: =E7+E8+E9 -> 359.24 | F10: =F7+F8+F9 -> 375.57852 | G10: =G7+G8+G9 -> 400.14184 | H10: =H7+H8+H9 -> 432.20008 | I10: =I7+I8+I9 -> 470.75792 | J10: =J7+J8+J9 -> 515.8055
A12: Accounts payable | B12: 64.11 | C12: 62.61 | D12: 68.96 | E12: 69.86 | F12: =IncomeStatement!F3*Assumptions!B13 -> 75.50807 | G12: =IncomeStatement!G3*Assumptions!C13 -> 80.793635 | H12: =IncomeStatement!H3*Assumptions!D13 -> 85.641253 | I12: =IncomeStatement!I3*Assumptions!E13 -> 89.923316 | J12: =IncomeStatement!J3*Assumptions!F13 -> 93.969865
A13: Other current liabilities | B13: 89.87 | C13: 82.7 | D13: 107.43 | E13: 95.77 | F13: =E13 -> 95.77 | G13: =F13 -> 95.77 | H13: =G13 -> 95.77 | I13: =H13 -> 95.77 | J13: =I13 -> 95.77
A14: Total current liabilities | B14: =B12+B13 -> 153.98 | C14: =C12+C13 -> 145.31 | D14: =D12+D13 -> 176.39 | E14: =E12+E13 -> 165.63 | F14: =F12+F13 -> 171.27807 | G14: =G12+G13 -> 176.56364 | H14: =H12+H13 -> 181.41125 | I14: =I12+I13 -> 185.69332 | J14: =J12+J13 -> 189.73987
A15: Non-current liabilities | B15: 148.1 | C15: 145.12 | D15: 131.64 | E15: 119.88 | F15: =E15 -> 119.88 | G15: =F15 -> 119.88 | H15: =G15 -> 119.88 | I15: =H15 -> 119.88 | J15: =I15 -> 119.88
A16: Total liabilities | B16: =B14+B15 -> 302.08 | C16: =C14+C15 -> 290.43 | D16: =D14+D15 -> 308.03 | E16: =E14+E15 -> 285.51 | F16: =F14+F15 -> 291.15807 | G16: =G14+G15 -> 296.44364 | H16: =H14+H15 -> 301.29125 | I16: =I14+I15 -> 305.57332 | J16: =J14+J15 -> 309.61987
A17: Stockholders' equity | B17: 50.67 | C17: 62.15 | D17: 56.95 | E17: 73.73 | F17: =E17+CashFlow!F3+CashFlow!F10+CashFlow!F11 -> 84.420453 | G17: =F17+CashFlow!G3+CashFlow!G10+CashFlow!G11 -> 103.69821 | H17: =G17+CashFlow!H3+CashFlow!H10+CashFlow!H11 -> 130.90883 | I17: =H17+CashFlow!I3+CashFlow!I10+CashFlow!I11 -> 165.1846 | J17: =I17+CashFlow!J3+CashFlow!J10+CashFlow!J11 -> 206.18563
A18: Balance check (must be 0) | B18: =B10-B16-B17 -> 0 | C18: =C10-C16-C17 -> 0 | D18: =D10-D16-D17 -> 0 | E18: =E10-E16-E17 -> 0 | F18: =F10-F16-F17 -> 0 | G18: =G10-G16-G17 -> 0 | H18: =H10-H16-H17 -> 0 | I18: =I10-I16-I17 -> 0 | J18: =J10-J16-J17 -> 0
A20: Simplified: 'other' asset/liability lines held at FY2025 levels through the projection. Debt inside non-current liabilities.

Sheet CashFlow
A1: AAPL — Cash Flow ($bn)
B2: FY2022 | C2: FY2023 | D2: FY2024 | E2: FY2025 | F2: FY2026E | G2: FY2027E | H2: FY2028E | I2: FY2029E | J2: FY2030E
A3: Net income | B3: =IncomeStatement!B16 -> 99.8 | C3: =IncomeStatement!C16 -> 97.01 | D3: =IncomeStatement!D16 -> 93.73 | E3: =IncomeStatement!E16 -> 112.01 | F3: =IncomeStatement!F16 -> 121.19045 | G3: =IncomeStatement!G16 -> 130.07775 | H3: =IncomeStatement!H16 -> 138.31062 | I3: =IncomeStatement!I16 -> 145.67577 | J3: =IncomeStatement!J16 -> 152.70103
A4: D&A | B4: 11.1 | C4: 11.52 | D4: 11.45 | E4: 11.7 | F4: =IncomeStatement!F3*Assumptions!B9 -> 12.584678 | G4: =IncomeStatement!G3*Assumptions!C9 -> 13.465606 | H4: =IncomeStatement!H3*Assumptions!D9 -> 14.273542 | I4: =IncomeStatement!I3*Assumptions!E9 -> 14.987219 | J4: =IncomeStatement!J3*Assumptions!F9 -> 15.661644
A5: (Incr)/decr in working capital | C5: =-((BalanceSheet!C4-BalanceSheet!B4)+(BalanceSheet!C5-BalanceSheet!B5)-(BalanceSheet!C12-BalanceSheet!B12)) -> -4.21 | D5: =-((BalanceSheet!D4-BalanceSheet!C4)+(BalanceSheet!D5-BalanceSheet!C5)-(BalanceSheet!D12-BalanceSheet!C12)) -> 1.49 | E5: =-((BalanceSheet!E4-BalanceSheet!D4)+(BalanceSheet!E5-BalanceSheet!D5)-(BalanceSheet!E12-BalanceSheet!D12)) -> -3.9 | F5: =-((BalanceSheet!F4-BalanceSheet!E4)+(BalanceSheet!F5-BalanceSheet!E5)-(BalanceSheet!F12-BalanceSheet!E12)) -> 1.7082624 | G5: =-((BalanceSheet!G4-BalanceSheet!F4)+(BalanceSheet!G5-BalanceSheet!F5)-(BalanceSheet!G12-BalanceSheet!F12)) -> 1.8247784 | H5: =-((BalanceSheet!H4-BalanceSheet!G4)+(BalanceSheet!H5-BalanceSheet!G5)-(BalanceSheet!H12-BalanceSheet!G12)) -> 1.6735824 | I5: =-((BalanceSheet!I4-BalanceSheet!H4)+(BalanceSheet!I5-BalanceSheet!H5)-(BalanceSheet!I12-BalanceSheet!H12)) -> 1.4783312 | J5: =-((BalanceSheet!J4-BalanceSheet!I4)+(BalanceSheet!J5-BalanceSheet!I5)-(BalanceSheet!J12-BalanceSheet!I12)) -> 1.3970229
A6: Other operating items | B6: 11.25 | C6: 6.23 | D6: 11.57 | E6: -8.33 | F6: 0 | G6: 0 | H6: 0 | I6: 0 | J6: 0
A7: Operating cash flow | B7: =B3+B4+B6 -> 122.15 | C7: =C3+C4+C5+C6 -> 110.55 | D7: =D3+D4+D5+D6 -> 118.24 | E7: =E3+E4+E5+E6 -> 111.48 | F7: =F3+F4+F5+F6 -> 135.48339 | G7: =G3+G4+G5+G6 -> 145.36814 | H7: =H3+H4+H5+H6 -> 154.25775 | I7: =I3+I4+I5+I6 -> 162.14132 | J7: =J3+J4+J5+J6 -> 169.7597
A8: Capital expenditure | B8: -10.71 | C8: -10.96 | D8: -9.45 | E8: -12.71 | F8: =-IncomeStatement!F3*Assumptions!B10 -> -13.483584 | G8: =-IncomeStatement!G3*Assumptions!C10 -> -14.427435 | H8: =-IncomeStatement!H3*Assumptions!D10 -> -15.293081 | I8: =-IncomeStatement!I3*Assumptions!E10 -> -16.057735 | J8: =-IncomeStatement!J3*Assumptions!F10 -> -16.780333
A9: Free cash flow | B9: =B7+B8 -> 111.44 | C9: =C7+C8 -> 99.59 | D9: =D7+D8 -> 108.79 | E9: =E7+E8 -> 98.77 | F9: =F7+F8 -> 121.99981 | G9: =G7+G8 -> 130.9407 | H9: =H7+H8 -> 138.96467 | I9: =I7+I8 -> 146.08359 | J9: =J7+J8 -> 152.97937
A10: Share repurchases | B10: -89.4 | C10: -77.55 | D10: -94.95 | E10: -90.71 | F10: =-Assumptions!B14 -> -95 | G10: =-Assumptions!C14 -> -95 | H10: =-Assumptions!D14 -> -95 | I10: =-Assumptions!E14 -> -95 | J10: =-Assumptions!F14 -> -95
A11: Dividends paid | B11: -14.84 | C11: -15.03 | D11: -15.23 | E11: -15.42 | F11: =-Assumptions!B15 -> -15.5 | G11: =-Assumptions!C15 -> -15.8 | H11: =-Assumptions!D15 -> -16.1 | I11: =-Assumptions!E15 -> -16.4 | J11: =-Assumptions!F15 -> -16.7
A12: Net cash generated | B12: =B9+B10+B11 -> 7.2 | C12: =C9+C10+C11 -> 7.01 | D12: =D9+D10+D11 -> -1.39 | E12: =E9+E10+E11 -> -7.36 | F12: =F9+F10+F11 -> 11.49981 | G12: =G9+G10+G11 -> 20.140702 | H12: =H9+H10+H11 -> 27.864668 | I12: =I9+I10+I11 -> 34.683588 | J12: =J9+J10+J11 -> 41.279365
A14: FY2022 working-capital move sits inside 'Other operating items' (no FY2021 balance sheet in the data pull).

Sheet DCF
A1: AAPL — Discounted Cash Flow
B2: FY2026E | C2: FY2027E | D2: FY2028E | E2: FY2029E | F2: FY2030E
A3: Free cash flow ($bn) | B3: =CashFlow!F9 -> 121.99981 | C3: =CashFlow!G9 -> 130.9407 | D3: =CashFlow!H9 -> 138.96467 | E3: =CashFlow!I9 -> 146.08359 | F3: =CashFlow!J9 -> 152.97937
A4: Discount period | B4: 1 | C4: 2 | D4: 3 | E4: 4 | F4: 5
A5: Discount factor | B5: =1/(1+Assumptions!$B$25)^B4 -> 0.9141948 | C5: =1/(1+Assumptions!$B$25)^C4 -> 0.83575214 | D5: =1/(1+Assumptions!$B$25)^D4 -> 0.76404026 | E5: =1/(1+Assumptions!$B$25)^E4 -> 0.69848164 | F5: =1/(1+Assumptions!$B$25)^F4 -> 0.63854828
A6: PV of FCF | B6: =B3*B5 -> 111.53159 | C6: =C3*C5 -> 109.43397 | D6: =D3*D5 -> 106.1746 | E6: =E3*E5 -> 102.0367 | F6: =F3*F5 -> 97.684711
A8: Sum PV of FCFs ($bn) | B8: =SUM(B6:F6) -> 526.86158
A9: Terminal value ($bn) | B9: =F3*(1+Assumptions!B26)/(Assumptions!B25-Assumptions!B26) -> 2467.4568
A10: PV of terminal value ($bn) | B10: =B9*F5 -> 1575.5903
A11: Enterprise value ($bn) | B11: =B8+B10 -> 2102.4519
A12: Less: net debt ($bn) | B12: =Assumptions!B31 -> 16.2
A13: Equity value ($bn) | B13: =B11-B12 -> 2086.2519
A14: Diluted shares (bn) | B14: =Assumptions!B30 -> 14.687
A15: DCF value per share | B15: =B13/B14 -> 142.04752
A16: Current share price | B16: =Assumptions!B29 -> 333.74
A17: Upside / (downside) | B17: =B15/B16-1 -> -0.57437671
A20: Sensitivity — value per share: WACC (rows) vs terminal growth (cols)
C21: 0.02 | D21: 0.025 | E21: 0.03 | F21: 0.035 | G21: 0.04
B22: 0.084 | C22: =(NPV($B22,$B$3:$F$3)+$F$3*(1+C$21)/($B22-C$21)/(1+$B22)^5-Assumptions!$B$31)/Assumptions!$B$30 -> 146.64883 | D22: =(NPV($B22,$B$3:$F$3)+$F$3*(1+D$21)/($B22-D$21)/(1+$B22)^5-Assumptions!$B$31)/Assumptions!$B$30 -> 156.6378 | E22: =(NPV($B22,$B$3:$F$3)+$F$3*(1+E$21)/($B22-E$21)/(1+$B22)^5-Assumptions!$B$31)/Assumptions!$B$30 -> 168.47657 | F22: =(NPV($B22,$B$3:$F$3)+$F$3*(1+F$21)/($B22-F$21)/(1+$B22)^5-Assumptions!$B$31)/Assumptions!$B$30 -> 182.73143 | G22: =(NPV($B22,$B$3:$F$3)+$F$3*(1+G$21)/($B22-G$21)/(1+$B22)^5-Assumptions!$B$31)/Assumptions!$B$30 -> 200.22602
B23: 0.089 | C23: =(NPV($B23,$B$3:$F$3)+$F$3*(1+C$21)/($B23-C$21)/(1+$B23)^5-Assumptions!$B$31)/Assumptions!$B$30 -> 135.77552 | D23: =(NPV($B23,$B$3:$F$3)+$F$3*(1+D$21)/($B23-D$21)/(1+$B23)^5-Assumptions!$B$31)/Assumptions!$B$30 -> 144.16102 | E23: =(NPV($B23,$B$3:$F$3)+$F$3*(1+E$21)/($B23-E$21)/(1+$B23)^5-Assumptions!$B$31)/Assumptions!$B$30 -> 153.9678 | F23: =(NPV($B23,$B$3:$F$3)+$F$3*(1+F$21)/($B23-F$21)/(1+$B23)^5-Assumptions!$B$31)/Assumptions!$B$30 -> 165.59065 | G23: =(NPV($B23,$B$3:$F$3)+$F$3*(1+G$21)/($B23-G$21)/(1+$B23)^5-Assumptions!$B$31)/Assumptions!$B$30 -> 179.5855
B24: 0.094 | C24: =(NPV($B24,$B$3:$F$3)+$F$3*(1+C$21)/($B24-C$21)/(1+$B24)^5-Assumptions!$B$31)/Assumptions!$B$30 -> 126.37422 | D24: =(NPV($B24,$B$3:$F$3)+$F$3*(1+D$21)/($B24-D$21)/(1+$B24)^5-Assumptions!$B$31)/Assumptions!$B$30 -> 133.49487 | E24: =(NPV($B24,$B$3:$F$3)+$F$3*(1+E$21)/($B24-E$21)/(1+$B24)^5-Assumptions!$B$31)/Assumptions!$B$30 -> 141.72812 | F24: =(NPV($B24,$B$3:$F$3)+$F$3*(1+F$21)/($B24-F$21)/(1+$B24)^5-Assumptions!$B$31)/Assumptions!$B$30 -> 151.35684 | G24: =(NPV($B24,$B$3:$F$3)+$F$3*(1+G$21)/($B24-G$21)/(1+$B24)^5-Assumptions!$B$31)/Assumptions!$B$30 -> 162.76865
B25: 0.099 | C25: =(NPV($B25,$B$3:$F$3)+$F$3*(1+C$21)/($B25-C$21)/(1+$B25)^5-Assumptions!$B$31)/Assumptions!$B$30 -> 118.16537 | D25: =(NPV($B25,$B$3:$F$3)+$F$3*(1+D$21)/($B25-D$21)/(1+$B25)^5-Assumptions!$B$31)/Assumptions!$B$30 -> 124.27226 | E25: =(NPV($B25,$B$3:$F$3)+$F$3*(1+E$21)/($B25-E$21)/(1+$B25)^5-Assumptions!$B$31)/Assumptions!$B$30 -> 131.26421 | F25: =(NPV($B25,$B$3:$F$3)+$F$3*(1+F$21)/($B25-F$21)/(1+$B25)^5-Assumptions!$B$31)/Assumptions!$B$30 -> 139.34865 | G25: =(NPV($B25,$B$3:$F$3)+$F$3*(1+G$21)/($B25-G$21)/(1+$B25)^5-Assumptions!$B$31)/Assumptions!$B$30 -> 148.80333
B26: 0.104 | C26: =(NPV($B26,$B$3:$F$3)+$F$3*(1+C$21)/($B26-C$21)/(1+$B26)^5-Assumptions!$B$31)/Assumptions!$B$30 -> 110.93599 | D26: =(NPV($B26,$B$3:$F$3)+$F$3*(1+D$21)/($B26-D$21)/(1+$B26)^5-Assumptions!$B$31)/Assumptions!$B$30 -> 116.21907 | E26: =(NPV($B26,$B$3:$F$3)+$F$3*(1+E$21)/($B26-E$21)/(1+$B26)^5-Assumptions!$B$31)/Assumptions!$B$30 -> 122.21608 | F26: =(NPV($B26,$B$3:$F$3)+$F$3*(1+F$21)/($B26-F$21)/(1+$B26)^5-Assumptions!$B$31)/Assumptions!$B$30 -> 129.08222 | G26: =(NPV($B26,$B$3:$F$3)+$F$3*(1+G$21)/($B26-G$21)/(1+$B26)^5-Assumptions!$B$31)/Assumptions!$B$30 -> 137.02119
A28: Gordon-growth terminal value. Base WACC and terminal growth set on Assumptions tab.

Sheet Comps
A1: AAPL — Trading Comparables
A2: Company | B2: Price | C2: Mkt cap ($bn) | D2: EV ($bn) | E2: P/E (TTM) | F2: P/E (fwd) | G2: EV/EBITDA | H2: Rev growth | I2: Net margin
A3: Apple (AAPL) | B3: 333.74 | C3: 4901.8 | D3: 4918 | E3: 40.5 | F3: 34.6 | G3: 30.7 | H3: 0.166 | I3: =IncomeStatement!E16/IncomeStatement!E3 -> 0.26915129
A4: Microsoft Corporation (MSFT) | B4: 393.82 | C4: 2925.5 | D4: 2972.7 | E4: 23.5 | F4: 20.3 | G4: 16.1 | H4: 0.183 | I4: 0.393
A5: Alphabet Inc. (GOOGL) | B5: 346.77 | C5: 4231.5 | D5: 4170.5 | E5: 26.5 | F5: 23.7 | G5: 25.9 | H5: 0.218 | I5: 0.379
A6: NVIDIA Corporation (NVDA) | B6: 202.81 | C6: 4912.3 | D6: 4867.6 | E6: 31.1 | F6: 15.8 | G6: 29.4 | H6: 0.852 | I6: 0.63
A7: Meta Platforms, Inc. (META) | B7: 646.01 | C7: 1639.8 | D7: 1645.4 | E7: 23.5 | F7: 17.8 | G7: 15.1 | H7: 0.331 | I7: 0.328
A8: Peer median (ex-AAPL) | E8: =MEDIAN(E4:E7) -> 25 | F8: =MEDIAN(F4:F7) -> 19.05 | G8: =MEDIAN(G4:G7) -> 21 | H8: =MEDIAN(H4:H7) -> 0.2745 | I8: =MEDIAN(I4:I7) -> 0.386
A10: AAPL premium to peer median (fwd P/E) | B10: =F3/F8-1 -> 0.81627297
A11: AAPL FY2026E EPS | B11: =IncomeStatement!F18 -> 8.2515458
A12: Implied value at peer-median fwd P/E | B12: =F8*B11 -> 157.19195
A14: Peer multiples: Yahoo Finance, 2026-07-18. Peer set: MSFT, GOOGL, NVDA, META (mega-cap tech).

Sheet SegmentRevenue
A1: AAPL — Revenue by Product Category ($bn)
B2: FY2022 | C2: FY2023 | D2: FY2024 | E2: FY2025
A3: iPhone | B3: 205.5 | C3: 200.6 | D3: 201.2 | E3: 209.6
A4: Mac | B4: 40.2 | C4: 29.4 | D4: 30 | E4: 33.7
A5: iPad | B5: 29.3 | C5: 28.3 | D5: 26.7 | E5: 28
A6: Wearables, Home & Accessories | B6: 41.2 | C6: 39.8 | D6: 37 | E6: 35.7
A7: Services | B7: 78.1 | C7: 85.2 | D7: 96.2 | E7: 109.2
A8: Total net sales | B8: =SUM(B3:B7) -> 394.3 | C8: =SUM(C3:C7) -> 383.3 | D8: =SUM(D3:D7) -> 391.1 | E8: =SUM(E3:E7) -> 416.2
A9: Tie to Income Statement (must be ~0) | B9: =B8-IncomeStatement!B3 -> -0.03 | C9: =C8-IncomeStatement!C3 -> 0.01 | D9: =D8-IncomeStatement!D3 -> 0.06 | E9: =E8-IncomeStatement!E3 -> 0.04
A11: Revenue mix (% of total)
A12: iPhone | B12: =B3/B$8 -> 0.52117677 | C12: =C3/C$8 -> 0.52334986 | D12: =D3/D$8 -> 0.51444643 | E12: =E3/E$8 -> 0.50360404
A13: Mac | B13: =B4/B$8 -> 0.10195283 | C13: =C4/C$8 -> 0.076702322 | D13: =D4/D$8 -> 0.076706725 | E13: =E4/E$8 -> 0.080970687
A14: iPad | B14: =B5/B$8 -> 0.074308902 | C14: =C5/C$8 -> 0.073832507 | D14: =D5/D$8 -> 0.068268985 | E14: =E5/E$8 -> 0.067275348
A15: Wearables, Home & Accessories | B15: =B6/B$8 -> 0.10448897 | C15: =C6/C$8 -> 0.10383512 | D15: =D6/D$8 -> 0.09460496 | E15: =E6/E$8 -> 0.085776069
A16: Services | B16: =B7/B$8 -> 0.19807253 | C16: =C7/C$8 -> 0.2222802 | D16: =D7/D$8 -> 0.2459729 | E16: =E7/E$8 -> 0.26237386
A18: Growth YoY
A19: iPhone | C19: =C3/B3-1 -> -0.023844282 | D19: =D3/C3-1 -> 0.0029910269 | E19: =E3/D3-1 -> 0.041749503
A20: Mac | C20: =C4/B4-1 -> -0.26865672 | D20: =D4/C4-1 -> 0.020408163 | E20: =E4/D4-1 -> 0.12333333
A21: iPad | C21: =C5/B5-1 -> -0.034129693 | D21: =D5/C5-1 -> -0.056537102 | E21: =E5/D5-1 -> 0.048689139
A22: Wearables, Home & Accessories | C22: =C6/B6-1 -> -0.033980583 | D22: =D6/C6-1 -> -0.070351759 | E22: =E6/D6-1 -> -0.035135135
A23: Services | C23: =C7/B7-1 -> 0.090909091 | D23: =D7/C7-1 -> 0.12910798 | E23: =E7/D7-1 -> 0.13513514
A25: Subscriptions — what Apple actually discloses
A26: Apple does NOT report subscription revenue as a separate line. The closest disclosed figure is the
A27: Services segment: $109.2bn in FY2025 (26.2% of revenue), first year above $100bn, growing ~14%/yr.
A28: Services bundles subscriptions (iCloud, Apple Music, TV+, Arcade, News+, Fitness+, AppleCare plans,
A29: third-party app subscriptions sold via App Store) together with App Store commissions, advertising,
A30: and payment services - so Services revenue overstates pure subscription revenue.
A31: Scale disclosure: Apple reports 'more than 1 billion' cumulative paid subscriptions across its
A32: platforms (crossed in Jan 2025; more than doubled over four years).
A33: Services carried a ~74% gross margin in recent years vs ~37% for products - the mix shift toward
A34: Services is the main driver of total gross margin rising from 43.3% (FY22) to 46.9% (FY25).
A36: Sources: Apple Form 10-K FY2025 (SEC EDGAR, aapl-20250927) and FY2023 10-K for FY2022 figures; Apple press disclosures for subscription counts.

Sheet Earnings
A1: AAPL — Earnings Review
A3: Last four reported quarters
A4: Quarter (cal.) | B4: EPS estimate | C4: EPS actual | D4: Surprise
A5: Jun 2025 (FQ3'25) | B5: 1.43 | C5: 1.57 | D5: 0.101
A6: Sep 2025 (FQ4'25) | B6: 1.77 | C6: 1.85 | D6: 0.045
A7: Dec 2025 (FQ1'26) | B7: 2.67 | C7: 2.84 | D7: 0.063
A8: Mar 2026 (FQ2'26) | B8: 1.94 | C8: 2.01 | D8: 0.035
A10: Latest quarter (Mar 2026) revenue ($bn) | B10: 111.2
A11: Year-ago quarter (Mar 2025) revenue ($bn) | B11: 95.4
A12: Revenue growth YoY | B12: =B10/B11-1 -> 0.16561845
A14: Next earnings date | B14: Jul 30, 2026
A15: Street EPS estimate for FQ3'26 | B15: 1.89
A17: Key takeaways
A18: 1. Four consecutive EPS beats; the Dec-2025 quarter beat by 6.3% and set a revenue record ($143.8bn).
A19: 2. Growth has re-accelerated: Mar-2026 quarter revenue up 16.6% YoY vs +6.4% for all of FY2025.
A20: 3. FY2025 gross margin reached 46.9% (up from 43.3% in FY2022) on services mix shift.
A21: 4. Street remains constructive (consensus 'buy') but the mean target sits below the current price,
A22: implying the market is pricing more growth than the average analyst model.
A24: EPS history: Yahoo Finance earnings data. Quarterly revenue: Yahoo Finance quarterly income statement.
